yixiangrpc/demo_pb2.py
yixiangrpc/demo_pb2_grpc.py
yixiangrpc-0.1.0.dist-info/WHEEL
yixiangrpc-0.1.0.dist-info/METADATA
yixiangrpc-0.1.0.dist-info/RECORD
